pdf_join/__init__.py
pdf_join/__main__.py
pdf_join/pdf_join.py
pdf_join-1.0.8.dist-info/licenses/LICENSE
pdf_join-1.0.8.dist-info/METADATA
pdf_join-1.0.8.dist-info/WHEEL
pdf_join-1.0.8.dist-info/entry_points.txt
pdf_join-1.0.8.dist-info/top_level.txt
pdf_join-1.0.8.dist-info/RECORD
