Metadata-Version: 2.4
Name: pdf_join
Version: 1.0.8
Summary: Join PDFs from the command line.
Author-email: Michael Wilson <mawilson@udel.edu>
Project-URL: Homepage, https://github.com/mawilson1234/pdf_join
Keywords: pdf,merge
Classifier: Development Status :: 4 - Beta
Classifier: Programming Language :: Python
Classifier: Programming Language :: Python :: 3
Requires-Python: >=3
License-File: LICENSE
Requires-Dist: PyPDF2>=3.0.0
Requires-Dist: tqdm
Dynamic: license-file
